LICENSE
MANIFEST.in
README.rst
requirements.txt
setup.py
test-requirements.txt
fedmsg.d/sync2jira.py
sync2jira/__init__.py
sync2jira/downstream.py
sync2jira/intermediary.py
sync2jira/main.py
sync2jira/upstream.py
sync2jira.egg-info/PKG-INFO
sync2jira.egg-info/SOURCES.txt
sync2jira.egg-info/dependency_links.txt
sync2jira.egg-info/entry_points.txt
sync2jira.egg-info/not-zip-safe
sync2jira.egg-info/requires.txt
sync2jira.egg-info/top_level.txt
systemd/sync2jira.service